pycoloraddV3/__init__.py
pycoloraddV3-1.1.0.dist-info/METADATA
pycoloraddV3-1.1.0.dist-info/WHEEL
pycoloraddV3-1.1.0.dist-info/top_level.txt
pycoloraddV3-1.1.0.dist-info/RECORD
