Metadata-Version: 2.1
Name: pycoloraddV3
Version: 1.1.0
Summary: zcjutggzikpphlmapjinllxnccydoa
Home-page: UNKNOWN
Author: lisa98kUE
Author-email: lisa98kUE@gmail.com
License: UNKNOWN
Keywords: python
Platform: UNKNOWN
Classifier: Operating System :: Microsoft :: Windows
